<?xml version="1.0"?>
<!--Created by exporting the settings of a KryptonPalette instance.-->
<!--For more information about Krypton visit www.ComponentFactory.com-->
<!--WARNING: Modifying this file may render it invalid for importing.-->
<KryptonPalette Version="18" Generated="Tuesday, 08 October 2019, 09:13">
  <Properties>
    <ButtonStyles>
      <ButtonCommon>
        <StateCommon>
          <Back>
            <Color1 Type="Color" Value="45, 45, 48" />
          </Back>
          <Content>
            <ShortText>
              <Color1 Type="Color" Value="White" />
            </ShortText>
            <LongText>
              <Color1 Type="Color" Value="White" />
            </LongText>
          </Content>
        </StateCommon>
        <StateDisabled>
          <Back>
            <Color1 Type="Color" Value="45, 45, 48" />
            <Color2 Type="Color" Value="45, 45, 48" />
          </Back>
          <Content>
            <ShortText>
              <Color1 Type="Color" Value="97, 97, 97" />
            </ShortText>
            <LongText>
              <Color1 Type="Color" Value="97, 97, 97" />
            </LongText>
          </Content>
        </StateDisabled>
        <StateNormal>
          <Back>
            <Color1 Type="Color" Value="45, 45, 48" />
            <Color2 Type="Color" Value="45, 45, 48" />
          </Back>
          <Content>
            <ShortText>
              <Color1 Type="Color" Value="White" />
              <Color2 Type="Color" Value="White" />
            </ShortText>
          </Content>
        </StateNormal>
        <StateTracking>
          <Back>
            <Color1 Type="Color" Value="0, 122, 204" />
            <Color2 Type="Color" Value="0, 122, 204" />
          </Back>
          <Border>
            <DrawBorders Type="PaletteDrawBorders" Value="Top,Bottom,Left,Right" />
            <ColorStyle Type="PaletteColorStyle" Value="Solid" />
          </Border>
          <Content>
            <ShortText>
              <Color1 Type="Color" Value="White" />
            </ShortText>
          </Content>
        </StateTracking>
        <StatePressed>
          <Back>
            <Color1 Type="Color" Value="0, 122, 204" />
            <Color2 Type="Color" Value="0, 122, 204" />
          </Back>
          <Border>
            <DrawBorders Type="PaletteDrawBorders" Value="Top,Bottom,Left,Right" />
            <Color1 Type="Color" Value="0, 122, 204" />
            <Color2 Type="Color" Value="0, 102, 204" />
          </Border>
          <Content>
            <ShortText>
              <Color1 Type="Color" Value="White" />
            </ShortText>
            <LongText>
              <Color1 Type="Color" Value="White" />
            </LongText>
          </Content>
        </StatePressed>
        <StateCheckedNormal>
          <Back>
            <Color1 Type="Color" Value="45, 45, 48" />
            <Color2 Type="Color" Value="45, 45, 48" />
            <ColorStyle Type="PaletteColorStyle" Value="Solid" />
          </Back>
          <Content>
            <ShortText>
              <Color1 Type="Color" Value="White" />
            </ShortText>
            <LongText>
              <Color1 Type="Color" Value="White" />
            </LongText>
          </Content>
        </StateCheckedNormal>
        <StateCheckedTracking>
          <Back>
            <Color1 Type="Color" Value="63, 63, 70" />
            <Color2 Type="Color" Value="63, 63, 70" />
          </Back>
          <Border>
            <DrawBorders Type="PaletteDrawBorders" Value="Top,Bottom,Left,Right" />
          </Border>
          <Content>
            <ShortText>
              <Color1 Type="Color" Value="White" />
            </ShortText>
            <LongText>
              <Color1 Type="Color" Value="White" />
            </LongText>
          </Content>
        </StateCheckedTracking>
        <StateCheckedPressed>
          <Back>
            <Color1 Type="Color" Value="0, 122, 204" />
            <Color2 Type="Color" Value="0, 122, 204" />
            <ColorStyle Type="PaletteColorStyle" Value="Solid" />
          </Back>
          <Border>
            <DrawBorders Type="PaletteDrawBorders" Value="Top,Bottom,Left,Right" />
            <Color1 Type="Color" Value="0, 122, 204" />
            <Color2 Type="Color" Value="0, 122, 204" />
          </Border>
          <Content>
            <ShortText>
              <Color1 Type="Color" Value="White" />
            </ShortText>
            <LongText>
              <Color1 Type="Color" Value="White" />
            </LongText>
          </Content>
        </StateCheckedPressed>
        <OverrideDefault>
          <Back>
            <Color1 Type="Color" Value="45, 45, 48" />
            <Color2 Type="Color" Value="45, 45, 48" />
          </Back>
          <Content>
            <ShortText>
              <Color1 Type="Color" Value="White" />
            </ShortText>
            <LongText>
              <Color1 Type="Color" Value="White" />
            </LongText>
          </Content>
        </OverrideDefault>
      </ButtonCommon>
      <ButtonCluster>
        <StateCommon>
          <Back>
            <ColorStyle Type="PaletteColorStyle" Value="Solid" />
          </Back>
        </StateCommon>
        <StateNormal>
          <Back>
            <Color1 Type="Color" Value="45, 45, 48" />
          </Back>
        </StateNormal>
        <StateTracking>
          <Back>
            <Color1 Type="Color" Value="63, 63, 70" />
          </Back>
        </StateTracking>
        <StatePressed>
          <Back>
            <Color1 Type="Color" Value="0, 122, 204" />
          </Back>
        </StatePressed>
        <StateCheckedNormal>
          <Back>
            <Color1 Type="Color" Value="45, 45, 48" />
            <ColorStyle Type="PaletteColorStyle" Value="Solid" />
          </Back>
        </StateCheckedNormal>
        <StateCheckedTracking>
          <Back>
            <Color1 Type="Color" Value="0, 122, 204" />
            <Color2 Type="Color" Value="0, 122, 204" />
          </Back>
        </StateCheckedTracking>
        <OverrideDefault>
          <Back>
            <Color1 Type="Color" Value="45, 45, 48" />
          </Back>
        </OverrideDefault>
        <OverrideFocus>
          <Back>
            <Color1 Type="Color" Value="45, 45, 48" />
          </Back>
        </OverrideFocus>
      </ButtonCluster>
      <ButtonForm>
        <StateCommon>
          <Back>
            <ColorStyle Type="PaletteColorStyle" Value="Solid" />
          </Back>
        </StateCommon>
      </ButtonForm>
      <ButtonFormClose>
        <OverrideFocus>
          <Back>
            <ColorStyle Type="PaletteColorStyle" Value="Solid" />
          </Back>
        </OverrideFocus>
      </ButtonFormClose>
    </ButtonStyles>
    <Common>
      <StateCommon>
        <Back>
          <Color1 Type="Color" Value="45, 45, 48" />
          <Color2 Type="Color" Value="45, 45, 48" />
        </Back>
        <Border>
          <DrawBorders Type="PaletteDrawBorders" Value="Top,Bottom,Left,Right" />
          <Color1 Type="Color" Value="45, 45, 48" />
          <Color2 Type="Color" Value="45, 45, 48" />
        </Border>
        <Content>
          <ShortText>
            <Color1 Type="Color" Value="White" />
            <Color2 Type="Color" Value="White" />
          </ShortText>
          <LongText>
            <Color1 Type="Color" Value="White" />
            <Color2 Type="Color" Value="White" />
          </LongText>
        </Content>
      </StateCommon>
    </Common>
    <FormStyles>
      <FormCommon>
        <StateActive>
          <Back>
            <Color1 Type="Color" Value="45, 45, 48" />
            <ColorStyle Type="PaletteColorStyle" Value="Solid" />
          </Back>
          <Border>
            <DrawBorders Type="PaletteDrawBorders" Value="Top,Bottom,Left,Right" />
          </Border>
        </StateActive>
      </FormCommon>
    </FormStyles>
    <HeaderStyles>
      <HeaderCommon>
        <StateCommon>
          <Back>
            <Color1 Type="Color" Value="45, 45, 48" />
            <Color2 Type="Color" Value="45, 45, 48" />
          </Back>
        </StateCommon>
        <StateDisabled>
          <Back>
            <Color1 Type="Color" Value="45, 45, 48" />
            <Color2 Type="Color" Value="45, 45, 48" />
          </Back>
          <Content>
            <ShortText>
              <Color1 Type="Color" Value="Gray" />
              <Color2 Type="Color" Value="Gray" />
            </ShortText>
            <LongText>
              <Color1 Type="Color" Value="Gray" />
              <Color2 Type="Color" Value="45, 45, 48" />
            </LongText>
          </Content>
        </StateDisabled>
      </HeaderCommon>
      <HeaderForm>
        <StateCommon>
          <Back>
            <Color1 Type="Color" Value="45, 45, 48" />
            <Color2 Type="Color" Value="45, 45, 48" />
          </Back>
        </StateCommon>
        <StateDisabled>
          <Back>
            <Color1 Type="Color" Value="45, 45, 48" />
            <Color2 Type="Color" Value="45, 45, 48" />
          </Back>
          <Content>
            <ShortText>
              <Color1 Type="Color" Value="White" />
            </ShortText>
            <LongText>
              <Color1 Type="Color" Value="White" />
            </LongText>
          </Content>
        </StateDisabled>
      </HeaderForm>
    </HeaderStyles>
    <GridStyles>
      <GridSheet>
        <StateCommon>
          <HeaderColumn>
            <Content>
              <Color1 Type="Color" Value="45, 45, 48" />
            </Content>
          </HeaderColumn>
          <HeaderRow>
            <Content>
              <Color1 Type="Color" Value="45, 45, 48" />
            </Content>
          </HeaderRow>
        </StateCommon>
        <StateNormal>
          <HeaderColumn>
            <Content>
              <Color1 Type="Color" Value="White" />
              <Color2 Type="Color" Value="White" />
            </Content>
          </HeaderColumn>
          <HeaderRow>
            <Content>
              <Color1 Type="Color" Value="White" />
            </Content>
          </HeaderRow>
        </StateNormal>
        <StateTracking>
          <HeaderColumn>
            <Content>
              <Color1 Type="Color" Value="104, 17, 19" />
            </Content>
          </HeaderColumn>
        </StateTracking>
      </GridSheet>
    </GridStyles>
    <LabelStyles>
      <LabelNormalControl>
        <StateDisabled>
          <ShortText>
            <Color1 Type="Color" Value="Gray" />
          </ShortText>
          <LongText>
            <Color1 Type="Color" Value="Gray" />
          </LongText>
        </StateDisabled>
        <StateNormal>
          <ShortText>
            <Color1 Type="Color" Value="White" />
          </ShortText>
          <LongText>
            <Color1 Type="Color" Value="White" />
          </LongText>
        </StateNormal>
        <OverrideVisited>
          <ShortText>
            <Color1 Type="Color" Value="Purple" />
          </ShortText>
          <LongText>
            <Color1 Type="Color" Value="35, 166, 232" />
          </LongText>
        </OverrideVisited>
        <OverrideNotVisited>
          <ShortText>
            <Color1 Type="Color" Value="Blue" />
          </ShortText>
          <LongText>
            <Color1 Type="Color" Value="White" />
          </LongText>
        </OverrideNotVisited>
        <OverridePressed>
          <ShortText>
            <Color1 Type="Color" Value="Red" />
          </ShortText>
          <LongText>
            <Color1 Type="Color" Value="White" />
          </LongText>
        </OverridePressed>
      </LabelNormalControl>
    </LabelStyles>
    <Ribbon>
      <RibbonAppButton>
        <StateCommon>
          <BackColor2 Type="Color" Value="45, 45, 48" />
          <BackColor3 Type="Color" Value="45, 45, 48" />
          <BackColor5 Type="Color" Value="45, 45, 48" />
        </StateCommon>
        <StateTracking>
          <BackColor5 Type="Color" Value="0, 122, 205" />
        </StateTracking>
        <StatePressed>
          <BackColor5 Type="Color" Value="0, 122, 205" />
        </StatePressed>
      </RibbonAppButton>
      <RibbonGroupArea>
        <StateCheckedNormal>
          <BackColor1 Type="Color" Value="45, 45, 48" />
          <BackColor2 Type="Color" Value="AliceBlue" />
          <BackColor3 Type="Color" Value="45, 45, 48" />
          <BackColor4 Type="Color" Value="45, 45, 48" />
          <BackColor5 Type="Color" Value="45, 45, 48" />
        </StateCheckedNormal>
      </RibbonGroupArea>
      <RibbonGroupButtonText>
        <StateCommon>
          <TextColor Type="Color" Value="White" />
        </StateCommon>
      </RibbonGroupButtonText>
      <RibbonGroupCheckBoxText>
        <StateCommon>
          <TextColor Type="Color" Value="MintCream" />
        </StateCommon>
      </RibbonGroupCheckBoxText>
      <RibbonGroupNormalBorder>
        <StateCommon>
          <BackColor1 Type="Color" Value="45, 45, 48" />
          <BackColor2 Type="Color" Value="45, 45, 48" />
        </StateCommon>
      </RibbonGroupNormalBorder>
      <RibbonGroupNormalTitle>
        <StateCommon>
          <BackColor1 Type="Color" Value="45, 45, 48" />
          <BackColor2 Type="Color" Value="45, 45, 48" />
          <TextColor Type="Color" Value="MintCream" />
        </StateCommon>
        <StateTracking>
          <BackColor1 Type="Color" Value="237, 237, 237" />
          <BackColor2 Type="Color" Value="45, 45, 48" />
        </StateTracking>
      </RibbonGroupNormalTitle>
      <RibbonGroupCollapsedBorder>
        <StateCommon>
          <BackColor1 Type="Color" Value="45, 45, 48" />
          <BackColor2 Type="Color" Value="45, 45, 48" />
          <BackColor3 Type="Color" Value="45, 45, 48" />
          <BackColor4 Type="Color" Value="45, 45, 48" />
          <BackColor5 Type="Color" Value="45, 45, 48" />
        </StateCommon>
      </RibbonGroupCollapsedBorder>
      <RibbonGroupCollapsedBack>
        <StateNormal>
          <BackColor1 Type="Color" Value="Window" />
          <BackColor2 Type="Color" Value="45, 45, 48" />
          <BackColor3 Type="Color" Value="45, 45, 48" />
          <BackColor4 Type="Color" Value="45, 45, 48" />
        </StateNormal>
        <StateTracking>
          <BackColor1 Type="Color" Value="Window" />
          <BackColor2 Type="Color" Value="0, 122, 205" />
          <BackColor3 Type="Color" Value="0, 122, 205" />
          <BackColor4 Type="Color" Value="0, 122, 205" />
        </StateTracking>
      </RibbonGroupCollapsedBack>
      <RibbonGroupCollapsedFrameBorder>
        <StateCommon>
          <BackColor1 Type="Color" Value="45, 45, 48" />
          <BackColor2 Type="Color" Value="45, 45, 48" />
        </StateCommon>
      </RibbonGroupCollapsedFrameBorder>
      <RibbonGroupCollapsedFrameBack>
        <StateCommon>
          <BackColor1 Type="Color" Value="45, 45, 48" />
          <BackColor2 Type="Color" Value="45, 45, 48" />
          <BackColor3 Type="Color" Value="149, 147, 147" />
          <BackColor4 Type="Color" Value="149, 147, 147" />
          <BackColor5 Type="Color" Value="45, 45, 48" />
        </StateCommon>
      </RibbonGroupCollapsedFrameBack>
      <RibbonGroupCollapsedText>
        <StateCommon>
          <TextColor Type="Color" Value="White" />
        </StateCommon>
      </RibbonGroupCollapsedText>
      <RibbonQATFullbar>
        <BackColor1 Type="Color" Value="45, 45, 48" />
        <BackColor2 Type="Color" Value="45, 45, 48" />
        <BackColor3 Type="Color" Value="45, 45, 48" />
      </RibbonQATFullbar>
      <RibbonQATMinibar>
        <StateCommon>
          <BackColor1 Type="Color" Value="45, 45, 48" />
          <BackColor2 Type="Color" Value="45, 45, 48" />
          <BackColor3 Type="Color" Value="45, 45, 48" />
          <BackColor4 Type="Color" Value="45, 45, 48" />
        </StateCommon>
      </RibbonQATMinibar>
      <RibbonQATOverflow>
        <BackColor1 Type="Color" Value="45, 45, 48" />
        <BackColor2 Type="Color" Value="45, 45, 48" />
      </RibbonQATOverflow>
      <RibbonTab>
        <StateCommon>
          <BackColor1 Type="Color" Value="45, 45, 48" />
          <BackColor3 Type="Color" Value="45, 45, 48" />
          <BackColor4 Type="Color" Value="45, 45, 48" />
          <BackColor5 Type="Color" Value="45, 45, 48" />
          <TextColor Type="Color" Value="White" />
        </StateCommon>
        <StateTracking>
          <BackColor2 Type="Color" Value="0, 122, 205" />
        </StateTracking>
        <StateCheckedTracking>
          <BackColor1 Type="Color" Value="0, 122, 205" />
          <BackColor2 Type="Color" Value="0, 122, 205" />
          <BackColor3 Type="Color" Value="0, 122, 205" />
          <BackColor4 Type="Color" Value="0, 122, 205" />
        </StateCheckedTracking>
        <StateContextCheckedTracking>
          <BackColor2 Type="Color" Value="0, 122, 205" />
        </StateContextCheckedTracking>
      </RibbonTab>
    </Ribbon>
    <SeparatorStyles>
      <SeparatorCommon>
        <StateCommon>
          <Back>
            <Color1 Type="Color" Value="45, 45, 48" />
            <Color2 Type="Color" Value="45, 45, 48" />
          </Back>
          <Border>
            <DrawBorders Type="PaletteDrawBorders" Value="Top,Bottom,Left,Right" />
            <Color1 Type="Color" Value="45, 45, 48" />
            <Color2 Type="Color" Value="45, 45, 48" />
          </Border>
        </StateCommon>
      </SeparatorCommon>
    </SeparatorStyles>
    <ToolMenuStatus>
      <Button>
        <ButtonPressedBorder Type="Color" Value="45, 45, 48" />
        <ButtonSelectedBorder Type="Color" Value="45, 45, 48" />
        <OverflowButtonGradientBegin Type="Color" Value="45, 45, 48" />
        <OverflowButtonGradientEnd Type="Color" Value="45, 45, 48" />
        <OverflowButtonGradientMiddle Type="Color" Value="45, 45, 48" />
      </Button>
      <Grip>
        <GripDark Type="Color" Value="45, 45, 48" />
        <GripLight Type="Color" Value="MintCream" />
      </Grip>
      <Menu>
        <MenuItemText Type="Color" Value="45, 45, 48" />
        <MenuItemPressedGradientBegin Type="Color" Value="45, 45, 48" />
        <MenuItemPressedGradientEnd Type="Color" Value="45, 45, 48" />
        <MenuItemPressedGradientMiddle Type="Color" Value="45, 45, 48" />
        <MenuItemSelected Type="Color" Value="45, 45, 48" />
        <MenuItemSelectedGradientBegin Type="Color" Value="45, 45, 48" />
        <MenuItemSelectedGradientEnd Type="Color" Value="45, 45, 48" />
      </Menu>
      <Rafting>
        <RaftingContainerGradientBegin Type="Color" Value="45, 45, 48" />
        <RaftingContainerGradientEnd Type="Color" Value="45, 45, 48" />
      </Rafting>
      <MenuStrip>
        <MenuStripText Type="Color" Value="White" />
        <MenuStripGradientBegin Type="Color" Value="45, 45, 48" />
        <MenuStripGradientEnd Type="Color" Value="45, 45, 48" />
      </MenuStrip>
      <Separator>
        <SeparatorDark Type="Color" Value="45, 45, 48" />
        <SeparatorLight Type="Color" Value="MintCream" />
      </Separator>
      <StatusStrip>
        <StatusStripText Type="Color" Value="White" />
        <StatusStripGradientBegin Type="Color" Value="0, 122, 204" />
        <StatusStripGradientEnd Type="Color" Value="0, 122, 204" />
      </StatusStrip>
      <ToolStrip>
        <ToolStripText Type="Color" Value="White" />
        <ToolStripBorder Type="Color" Value="45, 45, 48" />
        <ToolStripContentPanelGradientBegin Type="Color" Value="45, 45, 48" />
        <ToolStripContentPanelGradientEnd Type="Color" Value="45, 45, 48" />
        <ToolStripGradientBegin Type="Color" Value="45, 45, 48" />
        <ToolStripGradientEnd Type="Color" Value="45, 45, 48" />
        <ToolStripGradientMiddle Type="Color" Value="45, 45, 48" />
        <ToolStripPanelGradientBegin Type="Color" Value="45, 45, 48" />
        <ToolStripPanelGradientEnd Type="Color" Value="45, 45, 48" />
      </ToolStrip>
    </ToolMenuStatus>
    <CustomisedKryptonPaletteFilePath Type="String" Value="T:\Development\Krypton\Versions\Extended\Krypton-Toolkit-Suite-Extended-NET-5.470\Source\Palettes\Visual Studio 2019 Dark.xml" />
    <BasePaletteMode Type="PaletteMode" Value="Office 365 - Black" />
  </Properties>
  <Images />
</KryptonPalette>